_lab/__init__.py
_lab/lab.py
examples/__init__.py
examples/azure_examples.py
examples/gcs_examples.py
examples/local_examples.py
examples/s3_examples.py
exemples/__init__.py
exemples/local_exemples.py
exemples/s3_exemples.py
storage_tool/__init__.py
storage_tool/azure.py
storage_tool/base.py
storage_tool/data_processor.py
storage_tool/gcs.py
storage_tool/local.py
storage_tool/s3.py
tests/__init__.py
tests/test_aws_s3.py
tests/test_azure.py
storage_tool-1.2.2.dist-info/LICENSE
storage_tool-1.2.2.dist-info/METADATA
storage_tool-1.2.2.dist-info/WHEEL
storage_tool-1.2.2.dist-info/top_level.txt
storage_tool-1.2.2.dist-info/RECORD
