Metadata-Version: 2.1
Name: storage-tool
Version: 1.2.2
Summary: Package for manager files in differents storages
Home-page: UNKNOWN
Author: Claudio Vinicius Oliveira
Author-email: claudio.datascience@gmail.com
License: UNKNOWN
Platform: UNKNOWN
License-File: LICENSE
Requires-Dist: boto3 ==1.29.6
Requires-Dist: botocore ==1.32.6
Requires-Dist: jmespath ==1.0.1
Requires-Dist: numpy <1.26.2,>=1.19.5
Requires-Dist: pandas <2.1.3,>=1.1.5
Requires-Dist: python-dateutil ==2.8.2
Requires-Dist: pytz ==2023.3.post1
Requires-Dist: tzdata ==2023.3
Requires-Dist: s3transfer ==0.7.0
Requires-Dist: pyarrow ==14.0.1
Requires-Dist: urllib3 ==1.26.18
Requires-Dist: azure-core ==1.29.5
Requires-Dist: azure-identity ==1.15.0
Requires-Dist: azure-storage-blob ==12.19.0
Requires-Dist: certifi ==2023.11.17
Requires-Dist: cryptography ==41.0.7
Requires-Dist: requests ==2.31.0
Requires-Dist: msal ==1.25.0
Requires-Dist: msal-extensions ==1.0.0
Requires-Dist: google-cloud-storage ==2.16.0
Requires-Dist: gcloud ==0.18.3
